Metadata-Version: 2.4
Name: gecco
Version: 0.10.2
Summary: Gene Cluster prediction with Conditional random fields.
Author-email: Martin Larralde <martin.larralde@embl.de>, Laura Carroll <lmc297@cornell.edu>
License-Expression: GPL-3.0-or-later
Project-URL: Repository, https://github.com/zellerlab/GECCO
Project-URL: Bug Tracker, https://github.com/zellerlab/GECCO/issues
Project-URL: Changelog, https://github.com/zellerlab/GECCO/blob/master/CHANGELOG.md
Project-URL: Coverage, https://codecov.io/gh/zellerlab/GECCO/
Project-URL: Builds, https://git.embl.de/grp-zeller/GECCO/-/pipelines
Project-URL: Preprint, https://www.biorxiv.org/content/10.1101/2021.05.03.442509v1
Classifier: Development Status :: 4 - Beta
Classifier: Intended Audience :: Science/Research
Classifier: Operating System :: POSIX
Classifier: Programming Language :: Python :: 3
Classifier: Topic :: Scientific/Engineering :: Bio-Informatics
Classifier: Topic :: Scientific/Engineering :: Medical Science Apps.
Classifier: Typing :: Typed
Requires-Python: >=3.7
Requires-Dist: biopython~=1.73
Requires-Dist: importlib-metadata>=4.0; python_version < "3.10"
Requires-Dist: importlib-resources>=5.7; python_version < "3.11"
Requires-Dist: numpy<3.0,>=1.0
Requires-Dist: polars~=1.0
Requires-Dist: pyhmmer~=0.12.0
Requires-Dist: pyrodigal~=3.0
Requires-Dist: rich>=12.4.0
Requires-Dist: rich-argparse~=1.0
Requires-Dist: scikit-learn~=1.0
Requires-Dist: scipy~=1.4
Requires-Dist: sklearn-crfsuite~=0.5.0
Provides-Extra: train
Requires-Dist: statsmodels<0.15,>=0.13; extra == "train"
Provides-Extra: cli
Requires-Dist: argcomplete~=3.0; extra == "cli"
